focus_validator/__init__.py
focus_validator/config_objects/__init__.py
focus_validator/config_objects/common.py
focus_validator/config_objects/focus_to_pandera_schema_converter.py
focus_validator/config_objects/override.py
focus_validator/config_objects/rule.py
focus_validator/data_loaders/__init__.py
focus_validator/data_loaders/csv_data_loader.py
focus_validator/data_loaders/data_loader.py
focus_validator/data_loaders/parquet_data_loader.py
focus_validator/exceptions.py
focus_validator/main.py
focus_validator/outputter/__init__.py
focus_validator/outputter/outputter.py
focus_validator/outputter/outputter_console.py
focus_validator/outputter/outputter_unittest.py
focus_validator/rules/__init__.py
focus_validator/rules/base_rule_definitions/FV-D001-0001.yaml
focus_validator/rules/base_rule_definitions/FV-D001-0002.yaml
focus_validator/rules/base_rule_definitions/FV-D001-0003.yaml
focus_validator/rules/base_rule_definitions/FV-D001-0004.yaml
focus_validator/rules/base_rule_definitions/FV-D002-0001.yaml
focus_validator/rules/base_rule_definitions/FV-D002-0002.yaml
focus_validator/rules/base_rule_definitions/FV-D003-0001.yaml
focus_validator/rules/base_rule_definitions/FV-D003-0002.yaml
focus_validator/rules/base_rule_definitions/FV-D004-0001.yaml
focus_validator/rules/base_rule_definitions/FV-D004-0002.yaml
focus_validator/rules/base_rule_definitions/FV-D004-0003.yaml
focus_validator/rules/base_rule_definitions/FV-D005-0001.yaml
focus_validator/rules/base_rule_definitions/FV-D005-0002.yaml
focus_validator/rules/base_rule_definitions/FV-D005-0003.yaml
focus_validator/rules/base_rule_definitions/FV-D006-0001.yaml
focus_validator/rules/base_rule_definitions/FV-D006-0002.yaml
focus_validator/rules/base_rule_definitions/FV-D006-0003.yaml
focus_validator/rules/base_rule_definitions/FV-D007-0001.yaml
focus_validator/rules/base_rule_definitions/FV-D007-0002.yaml
focus_validator/rules/base_rule_definitions/FV-D007-0003.yaml
focus_spec_validator-0.5.4.dist-info/LICENSE
focus_spec_validator-0.5.4.dist-info/METADATA
focus_spec_validator-0.5.4.dist-info/WHEEL
focus_spec_validator-0.5.4.dist-info/entry_points.txt
focus_spec_validator-0.5.4.dist-info/RECORD
