Metadata-Version: 2.1
Name: focus-spec-validator
Version: 0.5.4
Summary: FOCUS spec validator.
Requires-Python: >=3.8.1,<4.0.0
Classifier: Programming Language :: Python :: 3
Classifier: Programming Language :: Python :: 3.9
Classifier: Programming Language :: Python :: 3.10
Classifier: Programming Language :: Python :: 3.11
Requires-Dist: pandas (>=1,<2)
Requires-Dist: pandera (>=0.16,<0.17)
Requires-Dist: pyarrow
Requires-Dist: pydantic (>=1,<2)
Requires-Dist: python-magic
Requires-Dist: pyyaml
Requires-Dist: requests
Requires-Dist: tabulate
